bye_cloud/__init__.py
bye_cloud/utils.py
bye_cloud-0.1.1.dist-info/WHEEL
bye_cloud-0.1.1.dist-info/entry_points.txt
bye_cloud-0.1.1.dist-info/METADATA
bye_cloud-0.1.1.dist-info/RECORD
