Metadata-Version: 2.3
Name: bye-cloud
Version: 0.1.1
Summary: Convert iCloud Photos backup to a useful folder structure
Author: Jake Kara
Author-email: Jake Kara <jake@jakekara.com>
Requires-Dist: tqdm>=4.67.1
Requires-Python: >=3.13
Project-URL: Documentation, https://github.com/yourusername/bye-cloud
Project-URL: Issues, https://github.com/yourusername/bye-cloud/issues
Project-URL: Source, https://github.com/yourusername/bye-cloud
